button_sync.v

/*
 * Autor:   Andrea García Borges
 * Fecha:   22/04/2026
 *
 * Módulo:  button_sync
 *
 * Descripción: Sincronizador de dos flip-flops para señales de botón
 *              provenientes de dominios asíncronos externos. Elimina el
 *              riesgo de metaestabilidad al capturar la señal en dos
 *              etapas consecutivas del dominio de reloj del sistema.
 *
 * Puertos:
 *   clk      Reloj del sistema
 *   btn_in   Señal de botón directa desde el pin físico
 *   btn_sync Señal sincronizada, libre de metaestabilidad
 */
module button_sync (
    input  wire clk,
    input  wire btn_in,
    output reg  btn_sync
);
    reg ff1;
 
    always @(posedge clk) begin
        ff1      <= btn_in;
        btn_sync <= ff1;
    end
 
endmodule

tb/tb_button_sync.sv
/*
 * Autor:   Andrea García Borges
 * Fecha:   23/04/2026
 *
 * Módulo:  tb_button_sync
 *
 * Descripción: Testbench de verificación para button_sync. Implementa una
 *              estructura de tester y scoreboard para validar el comportamiento
 *              del sincronizador de dos flip-flops bajo tres escenarios:
 *              verificación de propagación correcta de nivel alto y bajo,
 *              verificación de la latencia de registro ciclo a ciclo, y
 *              verificación de estabilidad ante señal sostenida sin glitches.
 *
 * Compilar:
 *   iverilog -g2012 -o tb_button_sync.vvp tb_button_sync.sv button_sync.v
 *
 * Ejecutar:
 *   vvp tb_button_sync.vvp
 */
`timescale 1ns/1ps
 
module tb_button_sync;
 
    bit  clk;
    bit  btn_in;
    wire btn_sync;
 
    int pass_count = 0;
    int fail_count = 0;
 
    button_sync u_dut (
        .clk     (clk),
        .btn_in  (btn_in),
        .btn_sync(btn_sync)
    );
 
    initial clk = 1'b0;
    always #5 clk = ~clk;
 
    // Aplica btn_in y verifica btn_sync exactamente dos ciclos despues.
    // Ciclo 1: ff1 captura btn_in
    // Ciclo 2: btn_sync captura ff1, punto de verificacion
    task automatic apply_and_check(
        input bit    in_val,
        input bit    exp_sync,
        input string descripcion
    );
        btn_in = in_val;
        @(posedge clk);
        @(posedge clk); #1;
 
        if (btn_sync === exp_sync) begin
            $display("  PASS: %-45s | btn_in=%b btn_sync=%b",
                     descripcion, in_val, btn_sync);
            pass_count++;
        end else begin
            $error("  FAIL: %-45s | btn_in=%b got btn_sync=%b expected %b",
                   descripcion, in_val, btn_sync, exp_sync);
            fail_count++;
        end
    endtask
 
    initial begin : tester
        $dumpfile("tb_button_sync.vcd");
        $dumpvars(0, tb_button_sync);
 
        btn_in = 1'b0;
        @(posedge clk);
        @(posedge clk);
 
        // Escenario 1: propagacion correcta de nivel alto y nivel bajo.
        // Confirma que btn_sync refleja btn_in exactamente dos ciclos despues.
        $display("");
        $display("Escenario 1: propagacion correcta de nivel alto y nivel bajo");
 
        apply_and_check(1'b0, 1'b0, "btn_in=0, btn_sync debe ser 0");
        apply_and_check(1'b1, 1'b1, "btn_in=1, btn_sync debe ser 1");
        apply_and_check(1'b0, 1'b0, "btn_in=0, btn_sync vuelve a 0");
        apply_and_check(1'b1, 1'b1, "btn_in=1, btn_sync vuelve a 1");
 
        // Escenario 2: latencia de registro ciclo a ciclo.
        // La salida NO cambia en el primer ciclo tras el cambio de entrada
        // y SI cambia en el segundo, verificando latencia de exactamente 2 posedges.
        $display("");
        $display("Escenario 2: latencia de registro ciclo a ciclo");
 
        apply_and_check(1'b0, 1'b0, "precondicion: btn_sync=0 estable");
 
        begin : blk_latencia_subida
            bit snap;
            btn_in = 1'b1;
            @(posedge clk); #1;
            snap = btn_sync;
            if (snap === 1'b0) begin
                $display("  PASS: %-45s | btn_sync=%b (sin cambio en ciclo 1)",
                         "latencia subida: ciclo 1", snap);
                pass_count++;
            end else begin
                $error("  FAIL: %-45s | btn_sync=%b esperado 0",
                       "latencia subida: ciclo 1", snap);
                fail_count++;
            end
            @(posedge clk); #1;
            if (btn_sync === 1'b1) begin
                $display("  PASS: %-45s | btn_sync=%b (actualizado en ciclo 2)",
                         "latencia subida: ciclo 2", btn_sync);
                pass_count++;
            end else begin
                $error("  FAIL: %-45s | btn_sync=%b esperado 1",
                       "latencia subida: ciclo 2", btn_sync);
                fail_count++;
            end
        end : blk_latencia_subida
 
        begin : blk_latencia_bajada
            bit snap;
            btn_in = 1'b0;
            @(posedge clk); #1;
            snap = btn_sync;
            if (snap === 1'b1) begin
                $display("  PASS: %-45s | btn_sync=%b (sin cambio en ciclo 1)",
                         "latencia bajada: ciclo 1", snap);
                pass_count++;
            end else begin
                $error("  FAIL: %-45s | btn_sync=%b esperado 1",
                       "latencia bajada: ciclo 1", snap);
                fail_count++;
            end
            @(posedge clk); #1;
            if (btn_sync === 1'b0) begin
                $display("  PASS: %-45s | btn_sync=%b (actualizado en ciclo 2)",
                         "latencia bajada: ciclo 2", btn_sync);
                pass_count++;
            end else begin
                $error("  FAIL: %-45s | btn_sync=%b esperado 0",
                       "latencia bajada: ciclo 2", btn_sync);
                fail_count++;
            end
        end : blk_latencia_bajada
 
        // Escenario 3: estabilidad ante señal sostenida.
        // btn_sync no debe generar glitches cuando btn_in permanece constante
        // durante multiples ciclos, tanto en nivel alto como en nivel bajo.
        $display("");
        $display("Escenario 3: estabilidad ante señal sostenida (sin glitches)");
 
        begin : blk_estabilidad_alta
            int i;
            bit fallo;
            fallo = 0;
            btn_in = 1'b1;
            @(posedge clk); @(posedge clk); #1;
            for (i = 0; i < 8; i++) begin
                if (btn_sync !== 1'b1) begin
                    $error("  FAIL: glitch btn_sync=%b en ciclo %0d (esperado 1)",
                           btn_sync, i);
                    fallo = 1;
                    fail_count++;
                end
                @(posedge clk); #1;
            end
            if (!fallo) begin
                $display("  PASS: %-45s | btn_sync=1 estable 8 ciclos",
                         "sin glitches con btn_in=1 sostenido");
                pass_count++;
            end
        end : blk_estabilidad_alta
 
        begin : blk_estabilidad_baja
            int i;
            bit fallo;
            fallo = 0;
            btn_in = 1'b0;
            @(posedge clk); @(posedge clk); #1;
            for (i = 0; i < 8; i++) begin
                if (btn_sync !== 1'b0) begin
                    $error("  FAIL: glitch btn_sync=%b en ciclo %0d (esperado 0)",
                           btn_sync, i);
                    fallo = 1;
                    fail_count++;
                end
                @(posedge clk); #1;
            end
            if (!fallo) begin
                $display("  PASS: %-45s | btn_sync=0 estable 8 ciclos",
                         "sin glitches con btn_in=0 sostenido");
                pass_count++;
            end
        end : blk_estabilidad_baja
 
        $display("");
        $display("================================================");
        $display("   SCOREBOARD FINAL");
        $display("   PASS : %0d", pass_count);
        $display("   FAIL : %0d", fail_count);
        $display("   TOTAL: %0d", pass_count + fail_count);
        $display("================================================");
        if (fail_count == 0)
            $display("   *** Todos los checks pasaron correctamente ***");
        else
            $display("   *** ATENCION: %0d check(s) fallaron ***", fail_count);
        $display("================================================");
 
        $finish;
    end : tester
 
endmodule : tb_button_sync

tb_button_sync.vcd
$date
	Thu Apr 23 14:11:40 2026
$end
$version
	Icarus Verilog
$end
$timescale
	1ps
$end
$scope module tb_button_sync $end
$var wire 1 ! btn_sync $end
$var reg 1 " btn_in $end
$var reg 1 # clk $end
$var integer 32 $ fail_count [31:0] $end
$var integer 32 % pass_count [31:0] $end
$scope module u_dut $end
$var wire 1 " btn_in $end
$var wire 1 # clk $end
$var reg 1 ! btn_sync $end
$var reg 1 & ff1 $end
$upscope $end
$scope begin tester $end
$scope begin blk_estabilidad_alta $end
$var reg 1 ' fallo $end
$var integer 32 ( i [31:0] $end
$upscope $end
$scope begin blk_estabilidad_baja $end
$var reg 1 ) fallo $end
$var integer 32 * i [31:0] $end
$upscope $end
$scope begin blk_latencia_bajada $end
$var reg 1 + snap $end
$upscope $end
$scope begin blk_latencia_subida $end
$var reg 1 , snap $end
$upscope $end
$upscope $end
$scope task apply_and_check $end
$upscope $end
$upscope $end
$enddefinitions $end
#0
$dumpvars
0,
0+
b0 *
0)
b0 (
0'
x&
b0 %
b0 $
0#
0"
x!
$end
#5000
0&
1#
#10000
0#
#15000
0!
1#
#20000
0#
#25000
1#
#30000
0#
#35000
1#
#36000
1"
b1 %
#40000
0#
#45000
1&
1#
#50000
0#
#55000
1!
1#
#56000
0"
b10 %
#60000
0#
#65000
0&
1#
#70000
0#
#75000
0!
1#
#76000
1"
b11 %
#80000
0#
#85000
1&
1#
#90000
0#
#95000
1!
1#
#96000
0"
b100 %
#100000
0#
#105000
0&
1#
#110000
0#
#115000
0!
1#
#116000
1"
b101 %
#120000
0#
#125000
1&
1#
#126000
b110 %
#130000
0#
#135000
1!
1#
#136000
0"
b111 %
#140000
0#
#145000
0&
1#
#146000
b1000 %
1+
#150000
0#
#155000
0!
1#
#156000
1"
b1001 %
#160000
0#
#165000
1&
1#
#170000
0#
#175000
1!
1#
#180000
0#
#185000
1#
#186000
b1 (
#190000
0#
#195000
1#
#196000
b10 (
#200000
0#
#205000
1#
#206000
b11 (
#210000
0#
#215000
1#
#216000
b100 (
#220000
0#
#225000
1#
#226000
b101 (
#230000
0#
#235000
1#
#236000
b110 (
#240000
0#
#245000
1#
#246000
b111 (
#250000
0#
#255000
1#
#256000
0"
b1010 %
b1000 (
#260000
0#
#265000
0&
1#
#270000
0#
#275000
0!
1#
#280000
0#
#285000
1#
#286000
b1 *
#290000
0#
#295000
1#
#296000
b10 *
#300000
0#
#305000
1#
#306000
b11 *
#310000
0#
#315000
1#
#316000
b100 *
#320000
0#
#325000
1#
#326000
b101 *
#330000
0#
#335000
1#
#336000
b110 *
#340000
0#
#345000
1#
#346000
b111 *
#350000
0#
#355000
1#
#356000
b1011 %
b1000 *
