edge_detector.v
/*
 * Autor:   Andrea García Borges
 * Fecha:   22/04/2026
 *
 * Módulo:  edge_detector
 *
 * Descripción: Detector de flanco de subida. Genera un pulso de exactamente
 *              un ciclo de reloj cuando detecta una transición de 0 a 1 en
 *              signal_in. Es el último eslabón de la cadena de
 *              acondicionamiento de botones.
 *
 * Puertos:
 *   clk        Reloj del sistema
 *   rst        Reset síncrono activo alto
 *   signal_in  Señal limpia procedente del debounce
 *   pulse_out  Pulso de 1 ciclo en cada flanco de subida
 */
module edge_detector (
    input  wire clk,
    input  wire rst,
    input  wire signal_in,
    output reg  pulse_out
);
    reg signal_d;
 
    always @(posedge clk) begin
        if (rst) begin
            signal_d  <= 1'b0;
            pulse_out <= 1'b0;
        end else begin
            pulse_out <= signal_in & ~signal_d;
            signal_d  <= signal_in;
        end
    end
 
endmodule

tb_edge_detector.sv
/*
 * Módulo:  tb_edge_detector
 *
 * Descripción: Testbench de verificación para edge_detector. Implementa una
 *              estructura de tester y scoreboard para validar el comportamiento
 *              del detector de flanco bajo tres escenarios: verificación de
 *              que un flanco de subida genera exactamente un pulso de un ciclo,
 *              verificación de que el flanco de bajada y el nivel sostenido no
 *              generan pulso adicional, y verificación del comportamiento ante
 *              múltiples flancos consecutivos y reset en medio de operación.
 *
 * Compilar:
 *   iverilog -g2012 -o tb_edge_detector.vvp tb_edge_detector.sv edge_detector.v
 *
 * Ejecutar:
 *   vvp tb_edge_detector.vvp
 */
`timescale 1ns/1ps
 
module tb_edge_detector;
 
    bit  clk;
    bit  rst;
    bit  signal_in;
    wire pulse_out;
 
    int pass_count = 0;
    int fail_count = 0;
 
    edge_detector u_dut (
        .clk       (clk),
        .rst       (rst),
        .signal_in (signal_in),
        .pulse_out (pulse_out)
    );
 
    initial clk = 1'b0;
    always #5 clk = ~clk;
 
    // Aplica signal_in y verifica pulse_out un ciclo despues.
    // El modulo registra en posedge, pulse_out refleja el flanco detectado
    // en el ciclo inmediatamente siguiente al cambio de entrada.
    task automatic apply_and_check(
        input bit    in_val,
        input bit    exp_pulse,
        input string descripcion
    );
        signal_in = in_val;
        @(posedge clk); #1;
 
        if (pulse_out === exp_pulse) begin
            $display("  PASS: %-45s | signal_in=%b pulse_out=%b",
                     descripcion, in_val, pulse_out);
            pass_count++;
        end else begin
            $error("  FAIL: %-45s | signal_in=%b got pulse_out=%b expected %b",
                   descripcion, in_val, pulse_out, exp_pulse);
            fail_count++;
        end
    endtask
 
    initial begin : tester
        $dumpfile("tb_edge_detector.vcd");
        $dumpvars(0, tb_edge_detector);
 
        rst       = 1'b1;
        signal_in = 1'b0;
        @(posedge clk); @(posedge clk);
        rst = 1'b0;
        @(posedge clk); #1;
 
        // Escenario 1: flanco de subida genera pulso de exactamente un ciclo.
        // La transicion de 0 a 1 debe producir pulse_out=1 durante un unico
        // ciclo y volver a 0 en el siguiente sin actividad adicional.
        $display("");
        $display("Escenario 1: flanco de subida genera pulso de un ciclo");
 
        apply_and_check(1'b0, 1'b0, "signal_in=0 estable, sin flanco, pulse_out=0");
        apply_and_check(1'b1, 1'b1, "flanco 0 a 1, pulse_out=1 en ciclo del flanco");
        apply_and_check(1'b1, 1'b0, "signal_in=1 sostenido ciclo 1, pulse_out vuelve a 0");
        apply_and_check(1'b1, 1'b0, "signal_in=1 sostenido ciclo 2, pulse_out=0");
 
        // Escenario 2: flanco de bajada y nivel sostenido no generan pulso.
        // La transicion de 1 a 0 no debe producir pulso. La señal baja
        // sostenida tampoco debe generar actividad en pulse_out.
        $display("");
        $display("Escenario 2: flanco de bajada y nivel sostenido no generan pulso");
 
        apply_and_check(1'b0, 1'b0, "flanco 1 a 0, pulse_out debe ser 0");
        apply_and_check(1'b0, 1'b0, "signal_in=0 sostenido ciclo 1, pulse_out=0");
        apply_and_check(1'b0, 1'b0, "signal_in=0 sostenido ciclo 2, pulse_out=0");
 
        begin : blk_sostenido_alto
            int i;
            bit fallo;
            fallo = 0;
            signal_in = 1'b1;
            @(posedge clk);           // ciclo del flanco: pulse_out=1
            @(posedge clk); #1;       // ciclo siguiente: pulse_out vuelve a 0
            for (i = 0; i < 6; i++) begin
                if (pulse_out !== 1'b0) begin
                    $error("  FAIL: glitch pulse_out=%b en ciclo sostenido %0d (esperado 0)",
                           pulse_out, i);
                    fallo = 1;
                    fail_count++;
                end
                @(posedge clk); #1;
            end
            if (!fallo) begin
                $display("  PASS: %-45s | pulse_out=0 estable 6 ciclos",
                         "sin glitches con signal_in=1 sostenido");
                pass_count++;
            end
        end : blk_sostenido_alto
 
        // Escenario 3: multiples flancos consecutivos y reset en operacion.
        // Cada transicion de 0 a 1 debe generar un pulso independiente.
        // El reset debe limpiar la salida de inmediato sin pulso residual.
        $display("");
        $display("Escenario 3: multiples flancos consecutivos y reset");
 
        apply_and_check(1'b0, 1'b0, "precondicion: signal_in=0, pulse_out=0");
        apply_and_check(1'b1, 1'b1, "flanco 1: pulse_out=1");
        apply_and_check(1'b0, 1'b0, "bajada entre flancos: pulse_out=0");
        apply_and_check(1'b1, 1'b1, "flanco 2: pulse_out=1");
        apply_and_check(1'b0, 1'b0, "bajada entre flancos: pulse_out=0");
        apply_and_check(1'b1, 1'b1, "flanco 3: pulse_out=1");
 
        begin : blk_reset
            signal_in = 1'b1;
            rst = 1'b1;
            @(posedge clk); #1;
            if (pulse_out === 1'b0) begin
                $display("  PASS: %-45s | pulse_out=%b (reset limpia salida)",
                         "reset activo fuerza pulse_out a 0", pulse_out);
                pass_count++;
            end else begin
                $error("  FAIL: %-45s | pulse_out=%b esperado 0",
                       "reset activo fuerza pulse_out a 0", pulse_out);
                fail_count++;
            end
            rst = 1'b0;
            signal_in = 1'b0;
            @(posedge clk); #1;
            if (pulse_out === 1'b0) begin
                $display("  PASS: %-45s | pulse_out=%b (sin pulso espurio)",
                         "post-reset sin pulso espurio en salida", pulse_out);
                pass_count++;
            end else begin
                $error("  FAIL: %-45s | pulse_out=%b esperado 0",
                       "post-reset sin pulso espurio en salida", pulse_out);
                fail_count++;
            end
        end : blk_reset
 
        $display("");
        $display("================================================");
        $display("   SCOREBOARD FINAL");
        $display("   PASS : %0d", pass_count);
        $display("   FAIL : %0d", fail_count);
        $display("   TOTAL: %0d", pass_count + fail_count);
        $display("================================================");
        if (fail_count == 0)
            $display("   *** Todos los checks pasaron correctamente ***");
        else
            $display("   *** ATENCION: %0d check(s) fallaron ***", fail_count);
        $display("================================================");
 
        $finish;
    end : tester
 
endmodule : tb_edge_detector

tb_edge_detector.vcd
$date
	Thu Apr 23 14:40:27 2026
$end
$version
	Icarus Verilog
$end
$timescale
	1ps
$end
$scope module tb_edge_detector $end
$var wire 1 ! pulse_out $end
$var reg 1 " clk $end
$var integer 32 # fail_count [31:0] $end
$var integer 32 $ pass_count [31:0] $end
$var reg 1 % rst $end
$var reg 1 & signal_in $end
$scope module u_dut $end
$var wire 1 " clk $end
$var wire 1 % rst $end
$var wire 1 & signal_in $end
$var reg 1 ! pulse_out $end
$var reg 1 ' signal_d $end
$upscope $end
$scope begin tester $end
$scope begin blk_reset $end
$upscope $end
$scope begin blk_sostenido_alto $end
$var reg 1 ( fallo $end
$var integer 32 ) i [31:0] $end
$upscope $end
$upscope $end
$scope task apply_and_check $end
$upscope $end
$upscope $end
$enddefinitions $end
#0
$dumpvars
b0 )
0(
x'
0&
1%
b0 $
b0 #
0"
x!
$end
#5000
0!
0'
1"
#10000
0"
#15000
0%
1"
#20000
0"
#25000
1"
#30000
0"
#35000
1"
#36000
1&
b1 $
#40000
0"
#45000
1'
1!
1"
#46000
b10 $
#50000
0"
#55000
0!
1"
#56000
b11 $
#60000
0"
#65000
1"
#66000
0&
b100 $
#70000
0"
#75000
0'
1"
#76000
b101 $
#80000
0"
#85000
1"
#86000
b110 $
#90000
0"
#95000
1"
#96000
1&
b111 $
#100000
0"
#105000
1'
1!
1"
#110000
0"
#115000
0!
1"
#120000
0"
#125000
1"
#126000
b1 )
#130000
0"
#135000
1"
#136000
b10 )
#140000
0"
#145000
1"
#146000
b11 )
#150000
0"
#155000
1"
#156000
b100 )
#160000
0"
#165000
1"
#166000
b101 )
#170000
0"
#175000
1"
#176000
0&
b1000 $
b110 )
#180000
0"
#185000
0'
1"
#186000
1&
b1001 $
#190000
0"
#195000
1'
1!
1"
#196000
0&
b1010 $
#200000
0"
#205000
0'
0!
1"
#206000
1&
b1011 $
#210000
0"
#215000
1'
1!
1"
#216000
0&
b1100 $
#220000
0"
#225000
0'
0!
1"
#226000
1&
b1101 $
#230000
0"
#235000
1'
1!
1"
#236000
1%
b1110 $
#240000
0"
#245000
0!
0'
1"
#246000
0&
0%
b1111 $
#250000
0"
#255000
1"
#256000
b10000 $
